SmartWaveAPI/SBL_sample.bin
SmartWaveAPI/__init__.py
SmartWaveAPI/newest_firmware.bin
SmartWaveAPI/newest_fpga_bitstream.bin
SmartWaveAPI/smartwave.py
SmartWaveAPI/configitems/__init__.py
SmartWaveAPI/configitems/config.py
SmartWaveAPI/configitems/driver.py
SmartWaveAPI/configitems/gpio.py
SmartWaveAPI/configitems/i2cconfig.py
SmartWaveAPI/configitems/i2cdriver.py
SmartWaveAPI/configitems/pin.py
SmartWaveAPI/configitems/spiconfig.py
SmartWaveAPI/configitems/spidriver.py
SmartWaveAPI/configitems/stimulus.py
SmartWaveAPI/definitions/__init__.py
SmartWaveAPI/definitions/command.py
SmartWaveAPI/definitions/drivertype.py
SmartWaveAPI/definitions/i2ctransaction.py
SmartWaveAPI/definitions/pinoutputtype.py
SmartWaveAPI/definitions/rgb565.py
SmartWaveAPI/definitions/statusbit.py
SmartWaveAPI/definitions/stimulustype.py
SmartWaveAPI/definitions/triggermode.py
smartwaveapi-2.1.3.dist-info/METADATA
smartwaveapi-2.1.3.dist-info/WHEEL
smartwaveapi-2.1.3.dist-info/licenses/LICENSE
smartwaveapi-2.1.3.dist-info/RECORD
