Metadata-Version: 2.3
Name: SmartWaveAPI
Version: 2.1.3
Summary: A python API for the SmartWave interface.
Project-URL: Homepage, https://semify-eda.github.io/wfg-API/docs/html/index.html
Author-email: Christoph Royer <mail@christophroyer.com>, Erwin Peterlin <erwin.peterlin@semify-eda.com>, Adam Horvath <adam.horvath@semify-eda.com>
License-File: LICENSE
Classifier: License :: OSI Approved :: MIT License
Classifier: Operating System :: OS Independent
Classifier: Programming Language :: Python :: 3
Requires-Python: >=3.8
Requires-Dist: pyserial==3.5
